{"config":{"output_file":null,"full_docs":false,"pub_only":true,"reachable_only":true,"distro_crate":false,"signatures":false,"borrow_data":false},"version":"0.19.0","compilation":{"directory":"C:\\Users\\chris\\.cargo\\registry\\src\\github.com-1ecc6299db9ec823\\num_cpus-1.13.0","program":"C:\\Users\\chris\\.rustup\\toolchains\\stable-x86_64-pc-windows-msvc\\bin\\rls.exe","arguments":["--crate-name","num_cpus","C:\\Users\\chris\\.cargo\\registry\\src\\github.com-1ecc6299db9ec823\\num_cpus-1.13.0\\src\\lib.rs","--json=diagnostic-rendered-ansi","--crate-type","lib","--emit=dep-info,metadata","-C","embed-bitcode=no","-C","codegen-units=4","-C","debuginfo=2","-C","metadata=fa37b08f54c5f0ab","-C","extra-filename=-fa37b08f54c5f0ab","--out-dir","d:\\Kenorld\\salvo\\examples\\hello_world\\target\\rls\\debug\\deps","-L","dependency=d:\\Kenorld\\salvo\\examples\\hello_world\\target\\rls\\debug\\deps","--extern","libc=d:\\Kenorld\\salvo\\examples\\hello_world\\target\\rls\\debug\\deps\\liblibc-7bcf56739d70e3f8.rmeta","--cap-lints","allow","--error-format=json","--sysroot","C:\\Users\\chris\\.rustup/toolchains/stable-x86_64-pc-windows-msvc"],"output":"d:\\Kenorld\\salvo\\examples\\hello_world\\target\\rls\\debug\\deps\\libnum_cpus-fa37b08f54c5f0ab.rmeta"},"prelude":{"crate_id":{"name":"num_cpus","disambiguator":[298938040438223827,570958154305529956]},"crate_root":"C:\\Users\\chris\\.cargo\\registry\\src\\github.com-1ecc6299db9ec823\\num_cpus-1.13.0\\src","external_crates":[{"file_name":"C:\\Users\\chris\\.cargo\\registry\\src\\github.com-1ecc6299db9ec823\\num_cpus-1.13.0\\src\\lib.rs","num":1,"id":{"name":"std","disambiguator":[2134305066550747688,1377703208702874155]}},{"file_name":"C:\\Users\\chris\\.cargo\\registry\\src\\github.com-1ecc6299db9ec823\\num_cpus-1.13.0\\src\\lib.rs","num":2,"id":{"name":"core","disambiguator":[1322159461575500717,8297198428669169011]}},{"file_name":"C:\\Users\\chris\\.cargo\\registry\\src\\github.com-1ecc6299db9ec823\\num_cpus-1.13.0\\src\\lib.rs","num":3,"id":{"name":"compiler_builtins","disambiguator":[2376346800744392852,12342541482992122530]}},{"file_name":"C:\\Users\\chris\\.cargo\\registry\\src\\github.com-1ecc6299db9ec823\\num_cpus-1.13.0\\src\\lib.rs","num":4,"id":{"name":"rustc_std_workspace_core","disambiguator":[14946502858004023242,6637215598610016319]}},{"file_name":"C:\\Users\\chris\\.cargo\\registry\\src\\github.com-1ecc6299db9ec823\\num_cpus-1.13.0\\src\\lib.rs","num":5,"id":{"name":"alloc","disambiguator":[5305136910335682758,6890491777619641650]}},{"file_name":"C:\\Users\\chris\\.cargo\\registry\\src\\github.com-1ecc6299db9ec823\\num_cpus-1.13.0\\src\\lib.rs","num":6,"id":{"name":"libc","disambiguator":[8079093424489733033,9678018066858265018]}},{"file_name":"C:\\Users\\chris\\.cargo\\registry\\src\\github.com-1ecc6299db9ec823\\num_cpus-1.13.0\\src\\lib.rs","num":7,"id":{"name":"unwind","disambiguator":[8191054904896780843,65190916132359678]}},{"file_name":"C:\\Users\\chris\\.cargo\\registry\\src\\github.com-1ecc6299db9ec823\\num_cpus-1.13.0\\src\\lib.rs","num":8,"id":{"name":"cfg_if","disambiguator":[17454577518104061478,8473922882117178851]}},{"file_name":"C:\\Users\\chris\\.cargo\\registry\\src\\github.com-1ecc6299db9ec823\\num_cpus-1.13.0\\src\\lib.rs","num":9,"id":{"name":"hashbrown","disambiguator":[14702801963282246562,3385633331338644346]}},{"file_name":"C:\\Users\\chris\\.cargo\\registry\\src\\github.com-1ecc6299db9ec823\\num_cpus-1.13.0\\src\\lib.rs","num":10,"id":{"name":"rustc_std_workspace_alloc","disambiguator":[4483555191844012602,617965746000623535]}},{"file_name":"C:\\Users\\chris\\.cargo\\registry\\src\\github.com-1ecc6299db9ec823\\num_cpus-1.13.0\\src\\lib.rs","num":11,"id":{"name":"rustc_demangle","disambiguator":[6496369475756502088,8603909216288097824]}},{"file_name":"C:\\Users\\chris\\.cargo\\registry\\src\\github.com-1ecc6299db9ec823\\num_cpus-1.13.0\\src\\lib.rs","num":12,"id":{"name":"panic_unwind","disambiguator":[8790568169648576788,8899032378407077408]}}],"span":{"file_name":"C:\\Users\\chris\\.cargo\\registry\\src\\github.com-1ecc6299db9ec823\\num_cpus-1.13.0\\src\\lib.rs","byte_start":0,"byte_end":12801,"line_start":1,"line_end":456,"column_start":1,"column_end":2}},"imports":[],"defs":[{"kind":"Mod","id":{"krate":0,"index":0},"span":{"file_name":"C:\\Users\\chris\\.cargo\\registry\\src\\github.com-1ecc6299db9ec823\\num_cpus-1.13.0\\src\\lib.rs","byte_start":0,"byte_end":12801,"line_start":1,"line_end":456,"column_start":1,"column_end":2},"name":"","qualname":"::","value":"C:\\Users\\chris\\.cargo\\registry\\src\\github.com-1ecc6299db9ec823\\num_cpus-1.13.0\\src\\lib.rs","parent":null,"children":[{"krate":0,"index":1},{"krate":0,"index":2},{"krate":0,"index":3},{"krate":0,"index":4},{"krate":0,"index":5},{"krate":0,"index":6},{"krate":0,"index":18}],"decl_id":null,"docs":" A crate with utilities to determine the number of CPUs available on the\n current system.","sig":null,"attributes":[{"value":"/ A crate with utilities to determine the number of CPUs available on the","span":{"file_name":"C:\\Users\\chris\\.cargo\\registry\\src\\github.com-1ecc6299db9ec823\\num_cpus-1.13.0\\src\\lib.rs","byte_start":0,"byte_end":75,"line_start":1,"line_end":1,"column_start":1,"column_end":76}},{"value":"/ current system.","span":{"file_name":"C:\\Users\\chris\\.cargo\\registry\\src\\github.com-1ecc6299db9ec823\\num_cpus-1.13.0\\src\\lib.rs","byte_start":76,"byte_end":95,"line_start":2,"line_end":2,"column_start":1,"column_end":20}},{"value":"/","span":{"file_name":"C:\\Users\\chris\\.cargo\\registry\\src\\github.com-1ecc6299db9ec823\\num_cpus-1.13.0\\src\\lib.rs","byte_start":96,"byte_end":99,"line_start":3,"line_end":3,"column_start":1,"column_end":4}},{"value":"/ Sometimes the CPU will exaggerate the number of CPUs it contains, because it can use","span":{"file_name":"C:\\Users\\chris\\.cargo\\registry\\src\\github.com-1ecc6299db9ec823\\num_cpus-1.13.0\\src\\lib.rs","byte_start":100,"byte_end":188,"line_start":4,"line_end":4,"column_start":1,"column_end":89}},{"value":"/ [processor tricks] to deliver increased performance when there are more threads. This ","span":{"file_name":"C:\\Users\\chris\\.cargo\\registry\\src\\github.com-1ecc6299db9ec823\\num_cpus-1.13.0\\src\\lib.rs","byte_start":189,"byte_end":279,"line_start":5,"line_end":5,"column_start":1,"column_end":91}},{"value":"/ crate provides methods to get both the logical and physical numbers of cores.","span":{"file_name":"C:\\Users\\chris\\.cargo\\registry\\src\\github.com-1ecc6299db9ec823\\num_cpus-1.13.0\\src\\lib.rs","byte_start":280,"byte_end":361,"line_start":6,"line_end":6,"column_start":1,"column_end":82}},{"value":"/","span":{"file_name":"C:\\Users\\chris\\.cargo\\registry\\src\\github.com-1ecc6299db9ec823\\num_cpus-1.13.0\\src\\lib.rs","byte_start":362,"byte_end":365,"line_start":7,"line_end":7,"column_start":1,"column_end":4}},{"value":"/ This information can be used as a guide to how many tasks can be run in parallel.","span":{"file_name":"C:\\Users\\chris\\.cargo\\registry\\src\\github.com-1ecc6299db9ec823\\num_cpus-1.13.0\\src\\lib.rs","byte_start":366,"byte_end":451,"line_start":8,"line_end":8,"column_start":1,"column_end":86}},{"value":"/ There are many properties of the system architecture that will affect parallelism,","span":{"file_name":"C:\\Users\\chris\\.cargo\\registry\\src\\github.com-1ecc6299db9ec823\\num_cpus-1.13.0\\src\\lib.rs","byte_start":452,"byte_end":538,"line_start":9,"line_end":9,"column_start":1,"column_end":87}},{"value":"/ for example memory access speeds (for all the caches and RAM) and the physical","span":{"file_name":"C:\\Users\\chris\\.cargo\\registry\\src\\github.com-1ecc6299db9ec823\\num_cpus-1.13.0\\src\\lib.rs","byte_start":539,"byte_end":621,"line_start":10,"line_end":10,"column_start":1,"column_end":83}},{"value":"/ architecture of the processor, so the number of CPUs should be used as a rough guide","span":{"file_name":"C:\\Users\\chris\\.cargo\\registry\\src\\github.com-1ecc6299db9ec823\\num_cpus-1.13.0\\src\\lib.rs","byte_start":622,"byte_end":710,"line_start":11,"line_end":11,"column_start":1,"column_end":89}},{"value":"/ only.","span":{"file_name":"C:\\Users\\chris\\.cargo\\registry\\src\\github.com-1ecc6299db9ec823\\num_cpus-1.13.0\\src\\lib.rs","byte_start":711,"byte_end":720,"line_start":12,"line_end":12,"column_start":1,"column_end":10}},{"value":"/","span":{"file_name":"C:\\Users\\chris\\.cargo\\registry\\src\\github.com-1ecc6299db9ec823\\num_cpus-1.13.0\\src\\lib.rs","byte_start":721,"byte_end":724,"line_start":13,"line_end":13,"column_start":1,"column_end":4}},{"value":"/","span":{"file_name":"C:\\Users\\chris\\.cargo\\registry\\src\\github.com-1ecc6299db9ec823\\num_cpus-1.13.0\\src\\lib.rs","byte_start":725,"byte_end":728,"line_start":14,"line_end":14,"column_start":1,"column_end":4}},{"value":"/ ## Examples","span":{"file_name":"C:\\Users\\chris\\.cargo\\registry\\src\\github.com-1ecc6299db9ec823\\num_cpus-1.13.0\\src\\lib.rs","byte_start":729,"byte_end":744,"line_start":15,"line_end":15,"column_start":1,"column_end":16}},{"value":"/","span":{"file_name":"C:\\Users\\chris\\.cargo\\registry\\src\\github.com-1ecc6299db9ec823\\num_cpus-1.13.0\\src\\lib.rs","byte_start":745,"byte_end":748,"line_start":16,"line_end":16,"column_start":1,"column_end":4}},{"value":"/ Fetch the number of logical CPUs.","span":{"file_name":"C:\\Users\\chris\\.cargo\\registry\\src\\github.com-1ecc6299db9ec823\\num_cpus-1.13.0\\src\\lib.rs","byte_start":749,"byte_end":786,"line_start":17,"line_end":17,"column_start":1,"column_end":38}},{"value":"/","span":{"file_name":"C:\\Users\\chris\\.cargo\\registry\\src\\github.com-1ecc6299db9ec823\\num_cpus-1.13.0\\src\\lib.rs","byte_start":787,"byte_end":790,"line_start":18,"line_end":18,"column_start":1,"column_end":4}},{"value":"/ ```","span":{"file_name":"C:\\Users\\chris\\.cargo\\registry\\src\\github.com-1ecc6299db9ec823\\num_cpus-1.13.0\\src\\lib.rs","byte_start":791,"byte_end":798,"line_start":19,"line_end":19,"column_start":1,"column_end":8}},{"value":"/ let cpus = num_cpus::get();","span":{"file_name":"C:\\Users\\chris\\.cargo\\registry\\src\\github.com-1ecc6299db9ec823\\num_cpus-1.13.0\\src\\lib.rs","byte_start":799,"byte_end":830,"line_start":20,"line_end":20,"column_start":1,"column_end":32}},{"value":"/ ```","span":{"file_name":"C:\\Users\\chris\\.cargo\\registry\\src\\github.com-1ecc6299db9ec823\\num_cpus-1.13.0\\src\\lib.rs","byte_start":831,"byte_end":838,"line_start":21,"line_end":21,"column_start":1,"column_end":8}},{"value":"/","span":{"file_name":"C:\\Users\\chris\\.cargo\\registry\\src\\github.com-1ecc6299db9ec823\\num_cpus-1.13.0\\src\\lib.rs","byte_start":839,"byte_end":842,"line_start":22,"line_end":22,"column_start":1,"column_end":4}},{"value":"/ See [`rayon::Threadpool`] for an example of where the number of CPUs could be","span":{"file_name":"C:\\Users\\chris\\.cargo\\registry\\src\\github.com-1ecc6299db9ec823\\num_cpus-1.13.0\\src\\lib.rs","byte_start":843,"byte_end":924,"line_start":23,"line_end":23,"column_start":1,"column_end":82}},{"value":"/ used when setting up parallel jobs (Where the threadpool example uses a fixed","span":{"file_name":"C:\\Users\\chris\\.cargo\\registry\\src\\github.com-1ecc6299db9ec823\\num_cpus-1.13.0\\src\\lib.rs","byte_start":925,"byte_end":1006,"line_start":24,"line_end":24,"column_start":1,"column_end":82}},{"value":"/ number 8, it could use the number of CPUs).","span":{"file_name":"C:\\Users\\chris\\.cargo\\registry\\src\\github.com-1ecc6299db9ec823\\num_cpus-1.13.0\\src\\lib.rs","byte_start":1007,"byte_end":1054,"line_start":25,"line_end":25,"column_start":1,"column_end":48}},{"value":"/","span":{"file_name":"C:\\Users\\chris\\.cargo\\registry\\src\\github.com-1ecc6299db9ec823\\num_cpus-1.13.0\\src\\lib.rs","byte_start":1055,"byte_end":1058,"line_start":26,"line_end":26,"column_start":1,"column_end":4}},{"value":"/ [processor tricks]: https://en.wikipedia.org/wiki/Simultaneous_multithreading","span":{"file_name":"C:\\Users\\chris\\.cargo\\registry\\src\\github.com-1ecc6299db9ec823\\num_cpus-1.13.0\\src\\lib.rs","byte_start":1059,"byte_end":1140,"line_start":27,"line_end":27,"column_start":1,"column_end":82}},{"value":"/ [`rayon::ThreadPool`]: https://docs.rs/rayon/1.*/rayon/struct.ThreadPool.html","span":{"file_name":"C:\\Users\\chris\\.cargo\\registry\\src\\github.com-1ecc6299db9ec823\\num_cpus-1.13.0\\src\\lib.rs","byte_start":1141,"byte_end":1222,"line_start":28,"line_end":28,"column_start":1,"column_end":82}},{"value":"deny(missing_docs)","span":{"file_name":"C:\\Users\\chris\\.cargo\\registry\\src\\github.com-1ecc6299db9ec823\\num_cpus-1.13.0\\src\\lib.rs","byte_start":1258,"byte_end":1280,"line_start":30,"line_end":30,"column_start":1,"column_end":23}},{"value":"allow(non_snake_case)","span":{"file_name":"C:\\Users\\chris\\.cargo\\registry\\src\\github.com-1ecc6299db9ec823\\num_cpus-1.13.0\\src\\lib.rs","byte_start":1340,"byte_end":1365,"line_start":32,"line_end":32,"column_start":1,"column_end":26}}]},{"kind":"Function","id":{"krate":0,"index":3},"span":{"file_name":"C:\\Users\\chris\\.cargo\\registry\\src\\github.com-1ecc6299db9ec823\\num_cpus-1.13.0\\src\\lib.rs","byte_start":2579,"byte_end":2582,"line_start":72,"line_end":72,"column_start":8,"column_end":11},"name":"get","qualname":"::get","value":"pub fn get() -> usize","parent":null,"children":[],"decl_id":null,"docs":" Returns the number of available CPUs of the current system.","sig":null,"attributes":[{"value":"/ Returns the number of available CPUs of the current system.","span":{"file_name":"C:\\Users\\chris\\.cargo\\registry\\src\\github.com-1ecc6299db9ec823\\num_cpus-1.13.0\\src\\lib.rs","byte_start":1581,"byte_end":1644,"line_start":45,"line_end":45,"column_start":1,"column_end":64}},{"value":"/","span":{"file_name":"C:\\Users\\chris\\.cargo\\registry\\src\\github.com-1ecc6299db9ec823\\num_cpus-1.13.0\\src\\lib.rs","byte_start":1645,"byte_end":1648,"line_start":46,"line_end":46,"column_start":1,"column_end":4}},{"value":"/ This function will get the number of logical cores. Sometimes this is different from the number","span":{"file_name":"C:\\Users\\chris\\.cargo\\registry\\src\\github.com-1ecc6299db9ec823\\num_cpus-1.13.0\\src\\lib.rs","byte_start":1649,"byte_end":1748,"line_start":47,"line_end":47,"column_start":1,"column_end":100}},{"value":"/ of physical cores (See [Simultaneous multithreading on Wikipedia][smt]).","span":{"file_name":"C:\\Users\\chris\\.cargo\\registry\\src\\github.com-1ecc6299db9ec823\\num_cpus-1.13.0\\src\\lib.rs","byte_start":1749,"byte_end":1825,"line_start":48,"line_end":48,"column_start":1,"column_end":77}},{"value":"/","span":{"file_name":"C:\\Users\\chris\\.cargo\\registry\\src\\github.com-1ecc6299db9ec823\\num_cpus-1.13.0\\src\\lib.rs","byte_start":1826,"byte_end":1829,"line_start":49,"line_end":49,"column_start":1,"column_end":4}},{"value":"/ # Examples","span":{"file_name":"C:\\Users\\chris\\.cargo\\registry\\src\\github.com-1ecc6299db9ec823\\num_cpus-1.13.0\\src\\lib.rs","byte_start":1830,"byte_end":1844,"line_start":50,"line_end":50,"column_start":1,"column_end":15}},{"value":"/","span":{"file_name":"C:\\Users\\chris\\.cargo\\registry\\src\\github.com-1ecc6299db9ec823\\num_cpus-1.13.0\\src\\lib.rs","byte_start":1845,"byte_end":1848,"line_start":51,"line_end":51,"column_start":1,"column_end":4}},{"value":"/ ```","span":{"file_name":"C:\\Users\\chris\\.cargo\\registry\\src\\github.com-1ecc6299db9ec823\\num_cpus-1.13.0\\src\\lib.rs","byte_start":1849,"byte_end":1856,"line_start":52,"line_end":52,"column_start":1,"column_end":8}},{"value":"/ let cpus = num_cpus::get();","span":{"file_name":"C:\\Users\\chris\\.cargo\\registry\\src\\github.com-1ecc6299db9ec823\\num_cpus-1.13.0\\src\\lib.rs","byte_start":1857,"byte_end":1888,"line_start":53,"line_end":53,"column_start":1,"column_end":32}},{"value":"/ if cpus > 1 {","span":{"file_name":"C:\\Users\\chris\\.cargo\\registry\\src\\github.com-1ecc6299db9ec823\\num_cpus-1.13.0\\src\\lib.rs","byte_start":1889,"byte_end":1906,"line_start":54,"line_end":54,"column_start":1,"column_end":18}},{"value":"/     println!(\"We are on a multicore system with {} CPUs\", cpus);","span":{"file_name":"C:\\Users\\chris\\.cargo\\registry\\src\\github.com-1ecc6299db9ec823\\num_cpus-1.13.0\\src\\lib.rs","byte_start":1907,"byte_end":1975,"line_start":55,"line_end":55,"column_start":1,"column_end":69}},{"value":"/ } else {","span":{"file_name":"C:\\Users\\chris\\.cargo\\registry\\src\\github.com-1ecc6299db9ec823\\num_cpus-1.13.0\\src\\lib.rs","byte_start":1976,"byte_end":1988,"line_start":56,"line_end":56,"column_start":1,"column_end":13}},{"value":"/     println!(\"We are on a single core system\");","span":{"file_name":"C:\\Users\\chris\\.cargo\\registry\\src\\github.com-1ecc6299db9ec823\\num_cpus-1.13.0\\src\\lib.rs","byte_start":1989,"byte_end":2040,"line_start":57,"line_end":57,"column_start":1,"column_end":52}},{"value":"/ }","span":{"file_name":"C:\\Users\\chris\\.cargo\\registry\\src\\github.com-1ecc6299db9ec823\\num_cpus-1.13.0\\src\\lib.rs","byte_start":2041,"byte_end":2046,"line_start":58,"line_end":58,"column_start":1,"column_end":6}},{"value":"/ ```","span":{"file_name":"C:\\Users\\chris\\.cargo\\registry\\src\\github.com-1ecc6299db9ec823\\num_cpus-1.13.0\\src\\lib.rs","byte_start":2047,"byte_end":2054,"line_start":59,"line_end":59,"column_start":1,"column_end":8}},{"value":"/","span":{"file_name":"C:\\Users\\chris\\.cargo\\registry\\src\\github.com-1ecc6299db9ec823\\num_cpus-1.13.0\\src\\lib.rs","byte_start":2055,"byte_end":2058,"line_start":60,"line_end":60,"column_start":1,"column_end":4}},{"value":"/ # Note","span":{"file_name":"C:\\Users\\chris\\.cargo\\registry\\src\\github.com-1ecc6299db9ec823\\num_cpus-1.13.0\\src\\lib.rs","byte_start":2059,"byte_end":2069,"line_start":61,"line_end":61,"column_start":1,"column_end":11}},{"value":"/","span":{"file_name":"C:\\Users\\chris\\.cargo\\registry\\src\\github.com-1ecc6299db9ec823\\num_cpus-1.13.0\\src\\lib.rs","byte_start":2070,"byte_end":2073,"line_start":62,"line_end":62,"column_start":1,"column_end":4}},{"value":"/ This will check [sched affinity] on Linux, showing a lower number of CPUs if the current","span":{"file_name":"C:\\Users\\chris\\.cargo\\registry\\src\\github.com-1ecc6299db9ec823\\num_cpus-1.13.0\\src\\lib.rs","byte_start":2074,"byte_end":2166,"line_start":63,"line_end":63,"column_start":1,"column_end":93}},{"value":"/ thread does not have access to all the computer's CPUs.","span":{"file_name":"C:\\Users\\chris\\.cargo\\registry\\src\\github.com-1ecc6299db9ec823\\num_cpus-1.13.0\\src\\lib.rs","byte_start":2167,"byte_end":2226,"line_start":64,"line_end":64,"column_start":1,"column_end":60}},{"value":"/","span":{"file_name":"C:\\Users\\chris\\.cargo\\registry\\src\\github.com-1ecc6299db9ec823\\num_cpus-1.13.0\\src\\lib.rs","byte_start":2227,"byte_end":2230,"line_start":65,"line_end":65,"column_start":1,"column_end":4}},{"value":"/ This will also check [cgroups], frequently used in containers to constrain CPU usage.","span":{"file_name":"C:\\Users\\chris\\.cargo\\registry\\src\\github.com-1ecc6299db9ec823\\num_cpus-1.13.0\\src\\lib.rs","byte_start":2231,"byte_end":2320,"line_start":66,"line_end":66,"column_start":1,"column_end":90}},{"value":"/","span":{"file_name":"C:\\Users\\chris\\.cargo\\registry\\src\\github.com-1ecc6299db9ec823\\num_cpus-1.13.0\\src\\lib.rs","byte_start":2321,"byte_end":2324,"line_start":67,"line_end":67,"column_start":1,"column_end":4}},{"value":"/ [smt]: https://en.wikipedia.org/wiki/Simultaneous_multithreading","span":{"file_name":"C:\\Users\\chris\\.cargo\\registry\\src\\github.com-1ecc6299db9ec823\\num_cpus-1.13.0\\src\\lib.rs","byte_start":2325,"byte_end":2393,"line_start":68,"line_end":68,"column_start":1,"column_end":69}},{"value":"/ [sched affinity]: http://www.gnu.org/software/libc/manual/html_node/CPU-Affinity.html","span":{"file_name":"C:\\Users\\chris\\.cargo\\registry\\src\\github.com-1ecc6299db9ec823\\num_cpus-1.13.0\\src\\lib.rs","byte_start":2394,"byte_end":2483,"line_start":69,"line_end":69,"column_start":1,"column_end":90}},{"value":"/ [cgroups]: https://www.kernel.org/doc/Documentation/cgroup-v1/cgroups.txt","span":{"file_name":"C:\\Users\\chris\\.cargo\\registry\\src\\github.com-1ecc6299db9ec823\\num_cpus-1.13.0\\src\\lib.rs","byte_start":2484,"byte_end":2561,"line_start":70,"line_end":70,"column_start":1,"column_end":78}},{"value":"inline","span":{"file_name":"C:\\Users\\chris\\.cargo\\registry\\src\\github.com-1ecc6299db9ec823\\num_cpus-1.13.0\\src\\lib.rs","byte_start":2562,"byte_end":2571,"line_start":71,"line_end":71,"column_start":1,"column_end":10}}]},{"kind":"Function","id":{"krate":0,"index":4},"span":{"file_name":"C:\\Users\\chris\\.cargo\\registry\\src\\github.com-1ecc6299db9ec823\\num_cpus-1.13.0\\src\\lib.rs","byte_start":3728,"byte_end":3740,"line_start":105,"line_end":105,"column_start":8,"column_end":20},"name":"get_physical","qualname":"::get_physical","value":"pub fn get_physical() -> usize","parent":null,"children":[],"decl_id":null,"docs":" Returns the number of physical cores of the current system.","sig":null,"attributes":[{"value":"/ Returns the number of physical cores of the current system.","span":{"file_name":"C:\\Users\\chris\\.cargo\\registry\\src\\github.com-1ecc6299db9ec823\\num_cpus-1.13.0\\src\\lib.rs","byte_start":2618,"byte_end":2681,"line_start":76,"line_end":76,"column_start":1,"column_end":64}},{"value":"/","span":{"file_name":"C:\\Users\\chris\\.cargo\\registry\\src\\github.com-1ecc6299db9ec823\\num_cpus-1.13.0\\src\\lib.rs","byte_start":2682,"byte_end":2685,"line_start":77,"line_end":77,"column_start":1,"column_end":4}},{"value":"/ # Note","span":{"file_name":"C:\\Users\\chris\\.cargo\\registry\\src\\github.com-1ecc6299db9ec823\\num_cpus-1.13.0\\src\\lib.rs","byte_start":2686,"byte_end":2696,"line_start":78,"line_end":78,"column_start":1,"column_end":11}},{"value":"/","span":{"file_name":"C:\\Users\\chris\\.cargo\\registry\\src\\github.com-1ecc6299db9ec823\\num_cpus-1.13.0\\src\\lib.rs","byte_start":2697,"byte_end":2700,"line_start":79,"line_end":79,"column_start":1,"column_end":4}},{"value":"/ Physical count is supported only on Linux, mac OS and Windows platforms.","span":{"file_name":"C:\\Users\\chris\\.cargo\\registry\\src\\github.com-1ecc6299db9ec823\\num_cpus-1.13.0\\src\\lib.rs","byte_start":2701,"byte_end":2777,"line_start":80,"line_end":80,"column_start":1,"column_end":77}},{"value":"/ On other platforms, or if the physical count fails on supported platforms,","span":{"file_name":"C:\\Users\\chris\\.cargo\\registry\\src\\github.com-1ecc6299db9ec823\\num_cpus-1.13.0\\src\\lib.rs","byte_start":2778,"byte_end":2856,"line_start":81,"line_end":81,"column_start":1,"column_end":79}},{"value":"/ this function returns the same as [`get()`], which is the number of logical","span":{"file_name":"C:\\Users\\chris\\.cargo\\registry\\src\\github.com-1ecc6299db9ec823\\num_cpus-1.13.0\\src\\lib.rs","byte_start":2857,"byte_end":2936,"line_start":82,"line_end":82,"column_start":1,"column_end":80}},{"value":"/ CPUS.","span":{"file_name":"C:\\Users\\chris\\.cargo\\registry\\src\\github.com-1ecc6299db9ec823\\num_cpus-1.13.0\\src\\lib.rs","byte_start":2937,"byte_end":2946,"line_start":83,"line_end":83,"column_start":1,"column_end":10}},{"value":"/","span":{"file_name":"C:\\Users\\chris\\.cargo\\registry\\src\\github.com-1ecc6299db9ec823\\num_cpus-1.13.0\\src\\lib.rs","byte_start":2947,"byte_end":2950,"line_start":84,"line_end":84,"column_start":1,"column_end":4}},{"value":"/ # Examples","span":{"file_name":"C:\\Users\\chris\\.cargo\\registry\\src\\github.com-1ecc6299db9ec823\\num_cpus-1.13.0\\src\\lib.rs","byte_start":2951,"byte_end":2965,"line_start":85,"line_end":85,"column_start":1,"column_end":15}},{"value":"/","span":{"file_name":"C:\\Users\\chris\\.cargo\\registry\\src\\github.com-1ecc6299db9ec823\\num_cpus-1.13.0\\src\\lib.rs","byte_start":2966,"byte_end":2969,"line_start":86,"line_end":86,"column_start":1,"column_end":4}},{"value":"/ ```","span":{"file_name":"C:\\Users\\chris\\.cargo\\registry\\src\\github.com-1ecc6299db9ec823\\num_cpus-1.13.0\\src\\lib.rs","byte_start":2970,"byte_end":2977,"line_start":87,"line_end":87,"column_start":1,"column_end":8}},{"value":"/ let logical_cpus = num_cpus::get();","span":{"file_name":"C:\\Users\\chris\\.cargo\\registry\\src\\github.com-1ecc6299db9ec823\\num_cpus-1.13.0\\src\\lib.rs","byte_start":2978,"byte_end":3017,"line_start":88,"line_end":88,"column_start":1,"column_end":40}},{"value":"/ let physical_cpus = num_cpus::get_physical();","span":{"file_name":"C:\\Users\\chris\\.cargo\\registry\\src\\github.com-1ecc6299db9ec823\\num_cpus-1.13.0\\src\\lib.rs","byte_start":3018,"byte_end":3067,"line_start":89,"line_end":89,"column_start":1,"column_end":50}},{"value":"/ if logical_cpus > physical_cpus {","span":{"file_name":"C:\\Users\\chris\\.cargo\\registry\\src\\github.com-1ecc6299db9ec823\\num_cpus-1.13.0\\src\\lib.rs","byte_start":3068,"byte_end":3105,"line_start":90,"line_end":90,"column_start":1,"column_end":38}},{"value":"/     println!(\"We have simultaneous multithreading with about {:.2} \\","span":{"file_name":"C:\\Users\\chris\\.cargo\\registry\\src\\github.com-1ecc6299db9ec823\\num_cpus-1.13.0\\src\\lib.rs","byte_start":3106,"byte_end":3178,"line_start":91,"line_end":91,"column_start":1,"column_end":73}},{"value":"/               logical cores to 1 physical core.\", ","span":{"file_name":"C:\\Users\\chris\\.cargo\\registry\\src\\github.com-1ecc6299db9ec823\\num_cpus-1.13.0\\src\\lib.rs","byte_start":3179,"byte_end":3233,"line_start":92,"line_end":92,"column_start":1,"column_end":55}},{"value":"/               (logical_cpus as f64) / (physical_cpus as f64));","span":{"file_name":"C:\\Users\\chris\\.cargo\\registry\\src\\github.com-1ecc6299db9ec823\\num_cpus-1.13.0\\src\\lib.rs","byte_start":3234,"byte_end":3300,"line_start":93,"line_end":93,"column_start":1,"column_end":67}},{"value":"/ } else if logical_cpus == physical_cpus {","span":{"file_name":"C:\\Users\\chris\\.cargo\\registry\\src\\github.com-1ecc6299db9ec823\\num_cpus-1.13.0\\src\\lib.rs","byte_start":3301,"byte_end":3346,"line_start":94,"line_end":94,"column_start":1,"column_end":46}},{"value":"/     println!(\"Either we don't have simultaneous multithreading, or our \\","span":{"file_name":"C:\\Users\\chris\\.cargo\\registry\\src\\github.com-1ecc6299db9ec823\\num_cpus-1.13.0\\src\\lib.rs","byte_start":3347,"byte_end":3423,"line_start":95,"line_end":95,"column_start":1,"column_end":77}},{"value":"/               system doesn't support getting the number of physical CPUs.\");","span":{"file_name":"C:\\Users\\chris\\.cargo\\registry\\src\\github.com-1ecc6299db9ec823\\num_cpus-1.13.0\\src\\lib.rs","byte_start":3424,"byte_end":3504,"line_start":96,"line_end":96,"column_start":1,"column_end":81}},{"value":"/ } else {","span":{"file_name":"C:\\Users\\chris\\.cargo\\registry\\src\\github.com-1ecc6299db9ec823\\num_cpus-1.13.0\\src\\lib.rs","byte_start":3505,"byte_end":3517,"line_start":97,"line_end":97,"column_start":1,"column_end":13}},{"value":"/     println!(\"We have less logical CPUs than physical CPUs, maybe we only have access to \\","span":{"file_name":"C:\\Users\\chris\\.cargo\\registry\\src\\github.com-1ecc6299db9ec823\\num_cpus-1.13.0\\src\\lib.rs","byte_start":3518,"byte_end":3612,"line_start":98,"line_end":98,"column_start":1,"column_end":95}},{"value":"/               some of the CPUs on our system.\");","span":{"file_name":"C:\\Users\\chris\\.cargo\\registry\\src\\github.com-1ecc6299db9ec823\\num_cpus-1.13.0\\src\\lib.rs","byte_start":3613,"byte_end":3665,"line_start":99,"line_end":99,"column_start":1,"column_end":53}},{"value":"/ }","span":{"file_name":"C:\\Users\\chris\\.cargo\\registry\\src\\github.com-1ecc6299db9ec823\\num_cpus-1.13.0\\src\\lib.rs","byte_start":3666,"byte_end":3671,"line_start":100,"line_end":100,"column_start":1,"column_end":6}},{"value":"/ ```","span":{"file_name":"C:\\Users\\chris\\.cargo\\registry\\src\\github.com-1ecc6299db9ec823\\num_cpus-1.13.0\\src\\lib.rs","byte_start":3672,"byte_end":3679,"line_start":101,"line_end":101,"column_start":1,"column_end":8}},{"value":"/","span":{"file_name":"C:\\Users\\chris\\.cargo\\registry\\src\\github.com-1ecc6299db9ec823\\num_cpus-1.13.0\\src\\lib.rs","byte_start":3680,"byte_end":3683,"line_start":102,"line_end":102,"column_start":1,"column_end":4}},{"value":"/ [`get()`]: fn.get.html","span":{"file_name":"C:\\Users\\chris\\.cargo\\registry\\src\\github.com-1ecc6299db9ec823\\num_cpus-1.13.0\\src\\lib.rs","byte_start":3684,"byte_end":3710,"line_start":103,"line_end":103,"column_start":1,"column_end":27}},{"value":"inline","span":{"file_name":"C:\\Users\\chris\\.cargo\\registry\\src\\github.com-1ecc6299db9ec823\\num_cpus-1.13.0\\src\\lib.rs","byte_start":3711,"byte_end":3720,"line_start":104,"line_end":104,"column_start":1,"column_end":10}}]}],"impls":[],"refs":[],"macro_refs":[],"relations":[]}